_version.py
chemparseplot/__init__.py
chemparseplot/basetypes.py
chemparseplot/units.py
chemparseplot/util.py
chemparseplot/analyze/dist.py
chemparseplot/analyze/use_ira.py
chemparseplot/parse/__init__.py
chemparseplot/parse/converter.py
chemparseplot/parse/patterns.py
chemparseplot/parse/eon/gprd.py
chemparseplot/parse/eon/minimization.py
chemparseplot/parse/eon/saddle_search.py
chemparseplot/parse/orca/__init__.py
chemparseplot/parse/orca/geomscan.py
chemparseplot/parse/orca/neb/interp.py
chemparseplot/parse/sella/saddle_search.py
chemparseplot/plot/__init__.py
chemparseplot/plot/_aids.py
chemparseplot/plot/geomscan.py
chemparseplot/plot/structs.py
tests/parse/test_converter.py
tests/parse/test_patterns.py
tests/parse/orca/test_geomscan.py
tests/parse/orca/test_interp.py
chemparseplot-0.0.3.dist-info/METADATA
chemparseplot-0.0.3.dist-info/WHEEL
chemparseplot-0.0.3.dist-info/licenses/LICENSE
chemparseplot-0.0.3.dist-info/RECORD
