Metadata-Version: 2.4
Name: chemparseplot
Version: 0.0.3
Summary: Parsers and plotting tools for computational chemistry
Project-URL: Documentation, https://github.com/HaoZeke/chemparseplot#readme
Project-URL: Issues, https://github.com/HaoZeke/chemparseplot/issues
Project-URL: Source, https://github.com/HaoZeke/chemparseplot
Author-email: Rohit Goswami <rog32@hi.is>
License: MIT
License-File: LICENSE
Keywords: compchem,parser,plot
Classifier: Development Status :: 4 - Beta
Classifier: Programming Language :: Python
Classifier: Programming Language :: Python :: 3 :: Only
Classifier: Programming Language :: Python :: 3.9
Classifier: Programming Language :: Python :: 3.10
Classifier: Programming Language :: Python :: 3.11
Classifier: Programming Language :: Python :: 3.12
Classifier: Programming Language :: Python :: Implementation :: CPython
Requires-Python: >=3.9
Requires-Dist: numpy>=1.26.2
Requires-Dist: pint>=0.22
Provides-Extra: doc
Requires-Dist: mdit-py-plugins>=0.3.4; extra == 'doc'
Requires-Dist: myst-nb>=1; extra == 'doc'
Requires-Dist: myst-parser>=2; extra == 'doc'
Requires-Dist: sphinx-autodoc2>=0.5; extra == 'doc'
Requires-Dist: sphinx-copybutton>=0.5.2; extra == 'doc'
Requires-Dist: sphinx-library>=1.1.2; extra == 'doc'
Requires-Dist: sphinx-sitemap>=2.5.1; extra == 'doc'
Requires-Dist: sphinx-togglebutton>=0.3.2; extra == 'doc'
Requires-Dist: sphinx>=7.2.6; extra == 'doc'
Requires-Dist: sphinxcontrib-apidoc>=0.4; extra == 'doc'
Provides-Extra: plot
Requires-Dist: cmcrameri>=1.7; extra == 'plot'
Requires-Dist: matplotlib>=3.8.2; extra == 'plot'
